stonemill/__init__.py
stonemill/stonemill.py
stonemill-0.2.2.dist-info/LICENSE
stonemill-0.2.2.dist-info/METADATA
stonemill-0.2.2.dist-info/WHEEL
stonemill-0.2.2.dist-info/entry_points.txt
stonemill-0.2.2.dist-info/top_level.txt
stonemill-0.2.2.dist-info/RECORD
