Metadata-Version: 2.1
Name: stonemill
Version: 0.2.2
Summary: A terraform scaffolding tool
Home-page: https://github.com/mirror12k/stonemill
Author: Mirror12k
License: MIT
Keywords: aws terraform scaffolding
Classifier: Programming Language :: Python :: 3
Classifier: License :: OSI Approved :: MIT License
License-File: LICENSE
